<annotation>
	<folder>100x</folder>
	<filename>Malaria_CM2_21Jun2021112924_0001_141.5_23.5_100x.png</filename>
	<path>D:\FYP\Monday Due\low_cost\CM2\Images\100x\Malaria_CM2_21Jun2021112924_0001_141.5_23.5_100x.png</path>
	<source>
		<database>Unknown</database>
	</source>
	<size>
		<width>395</width>
		<height>275</height>
		<depth>3</depth>
	</size>
	<segmented>0</segmented>
	<object>
		<name>ring</name>
		<pose>Unspecified</pose>
		<truncated>0</truncated>
		<difficult>0</difficult>
		<bndbox>
			<xmin>289</xmin>
			<ymin>189</ymin>
			<xmax>315</xmax>
			<ymax>214</ymax>
		</bndbox>
	</object>
	<object>
		<name>ring</name>
		<pose>Unspecified</pose>
		<truncated>0</truncated>
		<difficult>0</difficult>
		<bndbox>
			<xmin>209</xmin>
			<ymin>188</ymin>
			<xmax>228</xmax>
			<ymax>208</ymax>
		</bndbox>
	</object>
</annotation>
